juga/__init__.py
juga/__main__.py
juga/global_stock_scraper.py
juga/korea_stock_scraper.py
juga/metadata_scraper.py
juga/naver_stock_api.py
juga/naver_stock_models.py
juga/stock_scraper_base.py
juga-0.1.0.dist-info/LICENSE
juga-0.1.0.dist-info/METADATA
juga-0.1.0.dist-info/WHEEL
juga-0.1.0.dist-info/entry_points.txt
juga-0.1.0.dist-info/RECORD
