Metadata-Version: 2.1
Name: juga
Version: 0.1.0
Summary: 
Author: Chanwoong Kim
Author-email: me@chanwoong.kim
Requires-Python: >=3.9,<4.0
Classifier: Programming Language :: Python :: 3
Classifier: Programming Language :: Python :: 3.9
Classifier: Programming Language :: Python :: 3.10
Classifier: Programming Language :: Python :: 3.11
Requires-Dist: aiohttp (>=3.8.5,<4.0.0)
Requires-Dist: asyncache (>=0.3.1,<0.4.0)
Requires-Dist: bs4 (>=0.0.1,<0.0.2)
Requires-Dist: pydantic (>=2.3.0,<3.0.0)
Requires-Dist: typer (>=0.9.0,<0.10.0)
